_datasketches.cp311-win_amd64.pyd
datasketches/KernelFunction.py
datasketches/PySerDe.py
datasketches/TuplePolicy.py
datasketches/__init__.py
datasketches-5.2.0.dist-info/LICENSE
datasketches-5.2.0.dist-info/METADATA
datasketches-5.2.0.dist-info/NOTICE
datasketches-5.2.0.dist-info/WHEEL
datasketches-5.2.0.dist-info/top_level.txt
datasketches-5.2.0.dist-info/RECORD
