Metadata-Version: 2.2
Name: datasketches
Version: 5.2.0
Summary: The Apache DataSketches Library for Python
Home-page: http://datasketches.apache.org
Author: Apache Software Foundation
Author-email: dev@datasketches.apache.org
License: Apache License 2.0
License-File: LICENSE
License-File: NOTICE
Requires-Dist: numpy
Dynamic: author
Dynamic: author-email
Dynamic: description
Dynamic: description-content-type
Dynamic: home-page
Dynamic: license
Dynamic: requires-dist
Dynamic: summary
